{
  "id": "3197798",
  "name": "no name",
  "font_family": "iconfont",
  "css_prefix_text": "icon-",
  "description": "",
  "glyphs": [
    {
      "icon_id": "11372787",
      "name": "增加",
      "font_class": "zengjia",
      "unicode": "e8c8",
      "unicode_decimal": 59592
    },
    {
      "icon_id": "24942534",
      "name": "切换列表",
      "font_class": "qiehuanliebiao",
      "unicode": "e664",
      "unicode_decimal": 58980
    },
    {
      "icon_id": "8288999",
      "name": "加号",
      "font_class": "jiahao",
      "unicode": "e86a",
      "unicode_decimal": 59498
    },
    {
      "icon_id": "3374824",
      "name": "等待",
      "font_class": "dengdai",
      "unicode": "e663",
      "unicode_decimal": 58979
    },
    {
      "icon_id": "23174798",
      "name": "等待",
      "font_class": "dengdai1",
      "unicode": "e609",
      "unicode_decimal": 58889
    },
    {
      "icon_id": "13082370",
      "name": "终止",
      "font_class": "zhongzhi",
      "unicode": "e6e2",
      "unicode_decimal": 59106
    },
    {
      "icon_id": "19998904",
      "name": "已终止",
      "font_class": "yizhongzhi",
      "unicode": "e608",
      "unicode_decimal": 58888
    },
    {
      "icon_id": "10073439",
      "name": "错误",
      "font_class": "cuowu",
      "unicode": "e600",
      "unicode_decimal": 58880
    },
    {
      "icon_id": "8309282",
      "name": "成功-01",
      "font_class": "chenggong-",
      "unicode": "e661",
      "unicode_decimal": 58977
    },
    {
      "icon_id": "10666917",
      "name": "成功",
      "font_class": "chenggong5",
      "unicode": "e671",
      "unicode_decimal": 58993
    },
    {
      "icon_id": "8360881",
      "name": "成功",
      "font_class": "chenggong4",
      "unicode": "e6a9",
      "unicode_decimal": 59049
    },
    {
      "icon_id": "1951950",
      "name": "成功",
      "font_class": "chenggong",
      "unicode": "e61f",
      "unicode_decimal": 58911
    },
    {
      "icon_id": "7797608",
      "name": "成功",
      "font_class": "chenggong1",
      "unicode": "e60b",
      "unicode_decimal": 58891
    },
    {
      "icon_id": "14046406",
      "name": "对",
      "font_class": "chenggong2",
      "unicode": "e606",
      "unicode_decimal": 58886
    },
    {
      "icon_id": "19145276",
      "name": "成功",
      "font_class": "chenggong3",
      "unicode": "e620",
      "unicode_decimal": 58912
    },
    {
      "icon_id": "7934640",
      "name": "运行",
      "font_class": "yunhang5",
      "unicode": "e61d",
      "unicode_decimal": 58909
    },
    {
      "icon_id": "12771505",
      "name": "运行",
      "font_class": "yunhang4",
      "unicode": "e61b",
      "unicode_decimal": 58907
    },
    {
      "icon_id": "887857",
      "name": "暂停",
      "font_class": "zanting3",
      "unicode": "e61a",
      "unicode_decimal": 58906
    },
    {
      "icon_id": "10885300",
      "name": "暂停",
      "font_class": "zanting1",
      "unicode": "e612",
      "unicode_decimal": 58898
    },
    {
      "icon_id": "10885634",
      "name": "暂停",
      "font_class": "zanting2",
      "unicode": "e618",
      "unicode_decimal": 58904
    },
    {
      "icon_id": "7312242",
      "name": "运行",
      "font_class": "yunhang3",
      "unicode": "e613",
      "unicode_decimal": 58899
    },
    {
      "icon_id": "24079586",
      "name": "暂定_面",
      "font_class": "zanding_mian",
      "unicode": "e60d",
      "unicode_decimal": 58893
    },
    {
      "icon_id": "8962925",
      "name": "星星",
      "font_class": "xingxing1",
      "unicode": "e603",
      "unicode_decimal": 58883
    },
    {
      "icon_id": "9568056",
      "name": "星星-空",
      "font_class": "xingxing-kong",
      "unicode": "e649",
      "unicode_decimal": 58953
    },
    {
      "icon_id": "13788824",
      "name": "收藏",
      "font_class": "shoucang3",
      "unicode": "e604",
      "unicode_decimal": 58884
    },
    {
      "icon_id": "4174139",
      "name": "collision-runfails",
      "font_class": "yunhangshibai",
      "unicode": "e619",
      "unicode_decimal": 58905
    },
    {
      "icon_id": "6330337",
      "name": "运行",
      "font_class": "yunhang",
      "unicode": "e611",
      "unicode_decimal": 58897
    },
    {
      "icon_id": "7893806",
      "name": "运行",
      "font_class": "yunhang1",
      "unicode": "e68d",
      "unicode_decimal": 59021
    },
    {
      "icon_id": "11828683",
      "name": "运行失败",
      "font_class": "yunhangshibai1",
      "unicode": "e67a",
      "unicode_decimal": 59002
    },
    {
      "icon_id": "12676353",
      "name": "运行失败",
      "font_class": "yunhangshibai2",
      "unicode": "e61e",
      "unicode_decimal": 58910
    },
    {
      "icon_id": "23652374",
      "name": "运行失败",
      "font_class": "yunhangshibai3",
      "unicode": "e690",
      "unicode_decimal": 59024
    },
    {
      "icon_id": "25973796",
      "name": "收藏",
      "font_class": "shoucang1",
      "unicode": "e601",
      "unicode_decimal": 58881
    }
  ]
}
